hgan/__init__.py
hgan/__main__.py
hgan/_version.py
hgan/configuration.ini
hgan/configuration.py
hgan/dataset.py
hgan/demo.py
hgan/dm_datasets.py
hgan/logger.py
hgan/models.py
hgan/run.py
hgan/train.py
hgan/updates.py
hgan/utils.py
hgan/data/README.md
hgan/data/__init__.py
hgan/data/pendulum_colors/parameters.yaml
hgan/data/pendulum_colors/test/00000.npz
hgan/data/pendulum_colors/test/00001.npz
hgan/data/pendulum_colors/train/00000.npz
hgan/data/pendulum_colors/train/00001.npz
hgan/data/pendulum_colors/train/00002.npz
hgan/data/pendulum_colors/train/00003.npz
hgan/data/pendulum_colors/train/00004.npz
hgan/data/pendulum_colors/train/00005.npz
hgan/data/pendulum_colors/train/00006.npz
hgan/data/pendulum_colors/train/00007.npz
hgan/dm_hamiltonian_dynamics_suite/.pylintrc
hgan/dm_hamiltonian_dynamics_suite/__init__.py
hgan/dm_hamiltonian_dynamics_suite/datasets.py
hgan/dm_hamiltonian_dynamics_suite/generate_dataset.py
hgan/dm_hamiltonian_dynamics_suite/generate_locally.sh
hgan/dm_hamiltonian_dynamics_suite/load_datasets.py
hgan/dm_hamiltonian_dynamics_suite/hamiltonian_systems/__init__.py
hgan/dm_hamiltonian_dynamics_suite/hamiltonian_systems/hamiltonian.py
hgan/dm_hamiltonian_dynamics_suite/hamiltonian_systems/ideal_double_pendulum.py
hgan/dm_hamiltonian_dynamics_suite/hamiltonian_systems/ideal_mass_spring.py
hgan/dm_hamiltonian_dynamics_suite/hamiltonian_systems/ideal_pendulum.py
hgan/dm_hamiltonian_dynamics_suite/hamiltonian_systems/n_body.py
hgan/dm_hamiltonian_dynamics_suite/hamiltonian_systems/phase_space.py
hgan/dm_hamiltonian_dynamics_suite/hamiltonian_systems/simple_analytic.py
hgan/dm_hamiltonian_dynamics_suite/hamiltonian_systems/utils.py
hgan/dm_hamiltonian_dynamics_suite/molecular_dynamics/__init__.py
hgan/dm_hamiltonian_dynamics_suite/molecular_dynamics/generate_dataset.py
hgan/dm_hamiltonian_dynamics_suite/molecular_dynamics/lj_16.lmp
hgan/dm_hamiltonian_dynamics_suite/multiagent_dynamics/__init__.py
hgan-0.0.2.dist-info/METADATA
hgan-0.0.2.dist-info/WHEEL
hgan-0.0.2.dist-info/entry_points.txt
hgan-0.0.2.dist-info/top_level.txt
hgan-0.0.2.dist-info/RECORD
